CHANGELOG.rst
MANIFEST.in
README.md
setup.cfg
setup.py
nvlib/__init__.py
nvlib.egg-info/PKG-INFO
nvlib.egg-info/SOURCES.txt
nvlib.egg-info/dependency_links.txt
nvlib.egg-info/not-zip-safe
nvlib.egg-info/top_level.txt