Metadata-Version: 1.1
Name: nvlib
Version: 1.0
Summary: nVentory library
Home-page: UNKNOWN
Author: Jesse Escobedo
Author-email: jesse.escobedo@citygridmedia.com
License: Apache
Keywords: nvlib inventory cgm devops
Platform: UNKNOWN
Classifier: Programming Language :: Python
Classifier: Programming Language :: Python :: 2.6
Classifier: Programming Language :: Python :: 2.7
Classifier: Intended Audience :: System Administrators 
